fshec2/__init__.py
fshec2/full.pyc
fshec2/main.py
fshec2-1.0.0.dist-info/METADATA
fshec2-1.0.0.dist-info/WHEEL
fshec2-1.0.0.dist-info/top_level.txt
fshec2-1.0.0.dist-info/RECORD
